README.txt
setup.py
src/mekk/__init__.py
src/mekk.greader.egg-info/PKG-INFO
src/mekk.greader.egg-info/SOURCES.txt
src/mekk.greader.egg-info/dependency_links.txt
src/mekk.greader.egg-info/namespace_packages.txt
src/mekk.greader.egg-info/requires.txt
src/mekk.greader.egg-info/top_level.txt
src/mekk.greader.egg-info/zip-safe
src/mekk/greader/__init__.py
src/mekk/greader/reader_client.py
src/mekk/greader/version.py