Metadata-Version: 1.0
Name: mekk.greader
Version: 1.2.3
Summary: Simple wrapper for Google Reader API.
Home-page: http://bitbucket.org/Mekk/mekk.greader
Author: Marcin Kasperski
Author-email: Marcin.Kasperski@mekk.waw.pl
License: BSD
Keywords: google reader client
Platform: UNKNOWN
Classifier: Programming Language :: Python
Classifier: Intended Audience :: Developers
Classifier: Topic :: Software Development :: Libraries :: Python Modules
Classifier: Development Status :: 4 - Beta
Classifier: Environment :: Console
